pytars/__init__.py
pytars/readers/__init__.py
pytars/readers/maptiles/__init__.py
pytars/readers/maptiles/get_map_tiles.py
pytars/readers/maptiles/tile_servers.py
pytars/readers/pcap/__init__.py
pytars/readers/pcap/pcap_filters.py
pytars/readers/pcap/pcap_headers.py
pytars/readers/pcap/pcap_reader.py
pytars/sensors/__init__.py
pytars/sensors/lidar/__init__.py
pytars/sensors/lidar/pointcloud.py
pytars/transforms/__init__.py
pytars/transforms/cart2sph_coordinate_system.py
pytars/transforms/coordinates.py
pytars/transforms/transform.py
pytars/transforms/transform1d.py
pytars/transforms/transform3d.py
pytars/utils/__init__.py
pytars/utils/bin_edges.py
pytars/utils/custom_bathy_cmaps.py
pytars/utils/custom_cmaps.py
pytars/utils/get_project_path.py
pytars/utils/grid.py
pytars/utils/grid2d.py
pytars/utils/gridding.py
pytars/utils/random_names.py
pytars/utils/timing.py
pytars/utils/transforms.py
pytars-0.0.5.dist-info/LICENSE
pytars-0.0.5.dist-info/METADATA
pytars-0.0.5.dist-info/WHEEL
pytars-0.0.5.dist-info/top_level.txt
pytars-0.0.5.dist-info/RECORD
