Metadata-Version: 2.1
Name: pytars
Version: 0.0.5
Summary: Python Tools for Applied Remote Sensing
Author: hokiespurs
License-File: LICENSE
Requires-Dist: numpy
Requires-Dist: matplotlib
Requires-Dist: scipy
Requires-Dist: tqdm
Requires-Dist: requests
Requires-Dist: pillow
